[{"href":"http://www.pinterest.com/pin/409405422347909741/","board":"\n                        style.com\n        ","description":"NR","pin_page":"http://media-cache-ec0.pinimg.com/236x/04/2a/b2/042ab2fef63444ef8aa9b60371924d70.jpg","repins":"","likes":"","comments":""},{"href":"http://www.pinterest.com/pin/409405422347909726/","board":"\n                        style.com\n        ","description":"N.R.","pin_page":"http://media-cache-ec0.pinimg.com/236x/22/bf/10/22bf10ef2ac8b9ca3be193fe907a3103.jpg","repins":"","likes":"","comments":""},{"href":"http://www.pinterest.com/pin/409405422347909721/","board":"\n                        style.com\n        ","description":"N.R.","pin_page":"http://media-cache-ak0.pinimg.com/236x/ab/64/5b/ab645b92ab42619ec286b1f9091c38a6.jpg","repins":"","likes":"","comments":""},{"href":"http://www.pinterest.com/pin/409405422347909718/","board":"\n                        style.com\n        ","description":"N.r.","pin_page":"http://media-cache-ec0.pinimg.com/236x/e2/b9/e1/e2b9e1ddef2a7d4133c3626a050a7626.jpg","repins":"","likes":"","comments":""},{"href":"http://www.pinterest.com/pin/409405422347909714/","board":"\n                        style.com\n        ","description":"Narcisco Rodriguez","pin_page":"http://media-cache-ec0.pinimg.com/236x/d8/b4/5f/d8b45f782862646c7a17e4b31d2c77e3.jpg","repins":"","likes":"","comments":""},{"href":"http://www.pinterest.com/pin/409405422347909704/","board":"\n                        style.com\n        ","description":"Narciso Rodriguez | Fall 2014 Ready-to-Wear Collection | Style.com","pin_page":"http://media-cache-ec0.pinimg.com/236x/b5/74/43/b57443c04960ca04e40250c307209501.jpg","repins":"","likes":"","comments":""},{"href":"http://www.pinterest.com/pin/409405422347909598/","board":"\n                        style.com\n        ","description":"Calla | Fall 2014 Ready-to-Wear Collection | Style.com","pin_page":"http://media-cache-ec0.pinimg.com/236x/df/91/c4/df91c4064b059ddafb013a60f040a95e.jpg","repins":"","likes":"","comments":""},{"href":"http://www.pinterest.com/pin/409405422347909581/","board":"\n                        style.com\n        ","description":"Victoria Beckham | Fall 2014 Ready-to-Wear Collection | Style.com","pin_page":"http://media-cache-ak0.pinimg.com/236x/a6/a4/bc/a6a4bc238672aef014b97fbc9a4f2ce9.jpg","repins":"","likes":"","comments":""},{"href":"http://www.pinterest.com/pin/409405422347909556/","board":"\n                        style.com\n        ","description":"J.Crew | Fall 2014 Ready-to-Wear Collection | Style.com","pin_page":"http://media-cache-ec0.pinimg.com/236x/d1/52/c1/d152c14e926e9f0ad7ba5f7d53773ec8.jpg","repins":"","likes":"","comments":""},{"href":"http://www.pinterest.com/pin/409405422347906939/","board":"\n                        style.com\n        ","description":"I love the colors combination, length of the skirt, and comfy sweater/coat combination.","pin_page":"http://media-cache-ak0.pinimg.com/236x/fe/d8/7e/fed87e66efcdc4a50818ccad9654548d.jpg","repins":"","likes":"","comments":""}]